test/src/counter.v
module counter #(parameter W = 4)
                (input wire clk,
                 rst_n,
                 output reg [W-1:0] q);
    always @(posedge clk or negedge rst_n) begin
        if (!rst_n) q <= {W{1'b0}};
        else        q <= q + 1'b1;
    end
endmodule

test/tb/tb_counter.v
`timescale 1ns/1ps
module tb_counter;
  reg clk = 0, rst_n = 0;
  wire [3:0] q;

  counter #(.W(4)) dut(.clk(clk), .rst_n(rst_n), .q(q));

  // 파형 덤프
  initial begin
    $dumpfile("wave.vcd");
    $dumpvars(0, tb_counter);
  end

  // 클럭 10ns 주기
  always #5 clk = ~clk;

  initial begin
    #12  rst_n = 1;   // reset deassert
    #200 $finish;
  end
endmodule

test/wave.vcd
$date
	Fri Aug 15 11:02:40 2025
$end
$version
	Icarus Verilog
$end
$timescale
	1ps
$end
$scope module tb_counter $end
$var wire 4 ! q [3:0] $end
$var reg 1 " clk $end
$var reg 1 # rst_n $end
$scope module dut $end
$var wire 1 " clk $end
$var wire 1 # rst_n $end
$var reg 4 $ q [3:0] $end
$upscope $end
$upscope $end
$enddefinitions $end
#0
$dumpvars
bx $
0#
0"
bx !
$end
#5000
b0 !
b0 $
1"
#10000
0"
#12000
1#
#15000
b1 !
b1 $
1"
#20000
0"
#25000
b10 !
b10 $
1"
#30000
0"
#35000
b11 !
b11 $
1"
#40000
0"
#45000
b100 !
b100 $
1"
#50000
0"
#55000
b101 !
b101 $
1"
#60000
0"
#65000
b110 !
b110 $
1"
#70000
0"
#75000
b111 !
b111 $
1"
#80000
0"
#85000
b1000 !
b1000 $
1"
#90000
0"
#95000
b1001 !
b1001 $
1"
#100000
0"
#105000
b1010 !
b1010 $
1"
#110000
0"
#115000
b1011 !
b1011 $
1"
#120000
0"
#125000
b1100 !
b1100 $
1"
#130000
0"
#135000
b1101 !
b1101 $
1"
#140000
0"
#145000
b1110 !
b1110 $
1"
#150000
0"
#155000
b1111 !
b1111 $
1"
#160000
0"
#165000
b0 !
b0 $
1"
#170000
0"
#175000
b1 !
b1 $
1"
#180000
0"
#185000
b10 !
b10 $
1"
#190000
0"
#195000
b11 !
b11 $
1"
#200000
0"
#205000
b100 !
b100 $
1"
